README.md
setup.py
ttclust/__init__.py
ttclust/ttclustGUI.py
ttclustGUI.egg-info/PKG-INFO
ttclustGUI.egg-info/SOURCES.txt
ttclustGUI.egg-info/dependency_links.txt
ttclustGUI.egg-info/entry_points.txt
ttclustGUI.egg-info/requires.txt
ttclustGUI.egg-info/top_level.txt