Metadata-Version: 1.0
Name: ttclustGUI
Version: 1.0.2
Summary: A molecular simulation clustering program
Home-page: https://github.com/tubiana/TTClustGUI
Author: Thibault Tubiana
Author-email: tubiana.thibault@gmail.com
License: GPL3
Platform: Linux
Platform: Solaris
Platform: Mac OS-X
Platform: darwin
Platform: Unix
Platform: win32
